setup.cfg
setup.py
tunl/__init__.py
tunl/actions.py
tunl/api.py
tunl/data.py
tunl/parsing.py
tunl/schema.py
tunl/util.py
tunl/version.py
tunl.egg-info/PKG-INFO
tunl.egg-info/SOURCES.txt
tunl.egg-info/dependency_links.txt
tunl.egg-info/entry_points.txt
tunl.egg-info/requires.txt
tunl.egg-info/top_level.txt
tunl/bin/__init__.py
tunl/bin/_tunl.py
tunl/data/__init__.py