Metadata-Version: 1.1
Name: tunl
Version: 0.18
Summary: lightweight shh tunnel management utility.  supports command-line and programmatic usage
Home-page: https://github.com/mattvonrocketstein/tunl/
Author: mattvonrocketstein
Author-email: $author@gmail
License: UNKNOWN
Download-URL: https://github.com/mattvonrocketstein/tunl//tarball/master
Keywords: ssh,tunnel,manager
Platform: UNKNOWN
